{"html_attributions": [], "results": [{"business_status": "OPERATIONAL", "geometry": {"location": {"lat": 24.4393042, "lng": 86.01470839999999}, "viewport": {"northeast": {"lat": 24.4406631302915, "lng": 86.0161946302915}, "southwest": {"lat": 24.43796516970849, "lng": 86.01349666970849}}}, "icon": "https://maps.gstatic.com/mapfiles/place_api/icons/v1/png_71/shopping-71.png", "icon_background_color": "#4B96F3", "icon_mask_base_uri": "https://maps.gstatic.com/mapfiles/place_api/icons/v2/shoppingcart_pinlet", "name": "Ayush Traders", "opening_hours": {"open_now": true}, "place_id": "ChIJW3OxshDp8zkRVXLqmmNweKo", "reference": "ChIJW3OxshDp8zkRVXLqmmNweKo", "scope": "GOOGLE", "types": ["supermarket", "grocery_or_supermarket", "food", "point_of_interest", "store", "establishment"], "vicinity": "C2Q7+PVG, Banrhi"}], "status": "OK"}