{"html_attributions": [], "results": [{"business_status": "OPERATIONAL", "geometry": {"location": {"lat": 27.7876402, "lng": 80.5805037}, "viewport": {"northeast": {"lat": 27.7889216302915, "lng": 80.5818051802915}, "southwest": {"lat": 27.78622366970849, "lng": 80.57910721970849}}}, "icon": "https://maps.gstatic.com/mapfiles/place_api/icons/v1/png_71/school-71.png", "icon_background_color": "#7B9EB0", "icon_mask_base_uri": "https://maps.gstatic.com/mapfiles/place_api/icons/v2/school_pinlet", "name": "Government Primary School, Salahpur", "photos": [{"height": 3120, "html_attributions": ["<a href=\"https://maps.google.com/maps/contrib/105747689690120363982\">Devendra Kumar</a>"], "photo_reference": "Aap_uECmNl1IrVvL6qBFBHIcnNyowCfFe-SmomTrZ-UJXB2jRV96nhtoQ6xYbeLVzjwyXhBe7YFRE1CEkPCSM8PMixkSRzCbyHRiv0ZFEyn6Qz6A7uQcJOcRctW62hEDG2QTdgU59d0I9mp0UAaGt4B6hPCzjMCxXlBfJUO2a6Y9xCfS3Ka2", "width": 4160}], "place_id": "ChIJ3yllBtMknzkRJkt5aHVegxc", "rating": 5, "reference": "ChIJ3yllBtMknzkRJkt5aHVegxc", "scope": "GOOGLE", "types": ["primary_school", "school", "point_of_interest", "establishment"], "user_ratings_total": 1, "vicinity": "QHQJ+362, Kalliyarampur"}, {"business_status": "OPERATIONAL", "geometry": {"location": {"lat": 27.781512, "lng": 80.5975607}, "viewport": {"northeast": {"lat": 27.7827620302915, "lng": 80.59873738029151}, "southwest": {"lat": 27.7800640697085, "lng": 80.5960394197085}}}, "icon": "https://maps.gstatic.com/mapfiles/place_api/icons/v1/png_71/school-71.png", "icon_background_color": "#7B9EB0", "icon_mask_base_uri": "https://maps.gstatic.com/mapfiles/place_api/icons/v2/school_pinlet", "name": "P.S. KHANTA DESHU", "opening_hours": {"open_now": true}, "place_id": "ChIJoxRtxLclnzkRJAn4OZyadLA", "plus_code": {"compound_code": "QHJX+J2 Khantadesu, Uttar Pradesh, India", "global_code": "7MV2QHJX+J2"}, "rating": 5, "reference": "ChIJoxRtxLclnzkRJAn4OZyadLA", "scope": "GOOGLE", "types": ["primary_school", "school", "point_of_interest", "establishment"], "user_ratings_total": 1, "vicinity": "Khasta, rod, Khantadesu"}], "status": "OK"}