{"html_attributions": [], "results": [{"business_status": "OPERATIONAL", "geometry": {"location": {"lat": 26.4307438, "lng": 90.257592}, "viewport": {"northeast": {"lat": 26.4320898802915, "lng": 90.2589376802915}, "southwest": {"lat": 26.4293919197085, "lng": 90.25623971970847}}}, "icon": "https://maps.gstatic.com/mapfiles/place_api/icons/v1/png_71/generic_business-71.png", "icon_background_color": "#7B9EB0", "icon_mask_base_uri": "https://maps.gstatic.com/mapfiles/place_api/icons/v2/generic_pinlet", "name": "Reality public school chauraha", "place_id": "ChIJB0UTMbqLWDcRF_3IRC7cZ6M", "plus_code": {"compound_code": "C7J5+72 Boro Bhatarmari, Assam, India", "global_code": "7MRGC7J5+72"}, "reference": "ChIJB0UTMbqLWDcRF_3IRC7cZ6M", "scope": "GOOGLE", "types": ["taxi_stand", "point_of_interest", "establishment"], "vicinity": "Kokrajhar - Ramfalbil Road, Boro Bhatarmari"}], "status": "OK"}