{"html_attributions": [], "results": [{"business_status": "OPERATIONAL", "geometry": {"location": {"lat": 24.723871, "lng": 86.4275882}, "viewport": {"northeast": {"lat": 24.72955645, "lng": 86.42945238029151}, "southwest": {"lat": 24.72197585, "lng": 86.4267544197085}}}, "icon": "https://maps.gstatic.com/mapfiles/place_api/icons/v1/png_71/school-71.png", "icon_background_color": "#7B9EB0", "icon_mask_base_uri": "https://maps.gstatic.com/mapfiles/place_api/icons/v2/school_pinlet", "name": "LOGAI (BAJRANG BALI MANDIR)", "photos": [{"height": 1080, "html_attributions": ["<a href=\"https://maps.google.com/maps/contrib/102221068058971892767\">Monu kumar Rajak</a>"], "photo_reference": "Aap_uEAMophchxqE0b0b9nUxfXhG3-cgEklTvZon9vQFyRZBn05P1O7XHCWUy0BpSwgG3Cv5KFQus6uAdQBSWQ_nCeB_wsPqLFwI-6_TLbSewPkacDyGztfzPFB5-bRPG6otLiAukHoQox3VtoXOVQXf-RXJNfbwzzAAuaPUmdiquIcppgCd", "width": 1920}], "place_id": "ChIJE2d2jF5x8TkRqKuMAeujc5E", "rating": 4, "reference": "ChIJE2d2jF5x8TkRqKuMAeujc5E", "scope": "GOOGLE", "types": ["school", "point_of_interest", "establishment"], "user_ratings_total": 1, "vicinity": "PCFH+G2W, Tola Naugain"}, {"business_status": "OPERATIONAL", "geometry": {"location": {"lat": 24.72368759999999, "lng": 86.4266418}, "viewport": {"northeast": {"lat": 24.72983085, "lng": 86.42879729999999}, "southwest": {"lat": 24.72163984999999, "lng": 86.4259233}}}, "icon": "https://maps.gstatic.com/mapfiles/place_api/icons/v1/png_71/school-71.png", "icon_background_color": "#7B9EB0", "icon_mask_base_uri": "https://maps.gstatic.com/mapfiles/place_api/icons/v2/school_pinlet", "name": "Lok Shiksha Kendra Chain", "place_id": "ChIJ6_AIudRx8TkRhlyxswoTQww", "plus_code": {"compound_code": "PCFG+FM Tola Naugain, Bihar, India", "global_code": "7MP8PCFG+FM"}, "reference": "ChIJ6_AIudRx8TkRhlyxswoTQww", "scope": "GOOGLE", "types": ["school", "point_of_interest", "establishment"], "vicinity": "UMS, Tola Naugain"}, {"business_status": "OPERATIONAL", "geometry": {"location": {"lat": 24.7249255, "lng": 86.4279403}, "viewport": {"northeast": {"lat": 24.72900835, "lng": 86.42965928029152}, "southwest": {"lat": 24.72356455000001, "lng": 86.4269613197085}}}, "icon": "https://maps.gstatic.com/mapfiles/place_api/icons/v1/png_71/school-71.png", "icon_background_color": "#7B9EB0", "icon_mask_base_uri": "https://maps.gstatic.com/mapfiles/place_api/icons/v2/school_pinlet", "name": "Lok Shiksha Kendra Chain", "place_id": "ChIJg5ugNzVx8TkRFQfT-nNV_98", "reference": "ChIJg5ugNzVx8TkRFQfT-nNV_98", "scope": "GOOGLE", "types": ["school", "point_of_interest", "establishment"], "vicinity": "PCFH+X5G, Tola Naugain"}, {"business_status": "OPERATIONAL", "geometry": {"location": {"lat": 24.7196544, "lng": 86.4218313}, "viewport": {"northeast": {"lat": 24.7210145802915, "lng": 86.4231171802915}, "southwest": {"lat": 24.7183166197085, "lng": 86.42041921970849}}}, "icon": "https://maps.gstatic.com/mapfiles/place_api/icons/v1/png_71/school-71.png", "icon_background_color": "#7B9EB0", "icon_mask_base_uri": "https://maps.gstatic.com/mapfiles/place_api/icons/v2/school_pinlet", "name": "Parasi School", "opening_hours": {"open_now": true}, "photos": [{"height": 1080, "html_attributions": ["<a href=\"https://maps.google.com/maps/contrib/115671111569675308686\">Pintu Kumar</a>"], "photo_reference": "Aap_uEAN7cLF10MKK9m9WipzGFc-2kpJpuAWeq6ckwUo5Cd_PpIOWj4opG7ivm-fB1oiv6b0NDLIRfArRl1OTlj07zIELB-YuxpgBubegflEWaKnX2DpwoxVQ0xfYvThu0N749UeSHPQkdw8goAmRbC0qcqIByXWOmy6ilLa-lFXoeQmLY0u", "width": 1920}], "place_id": "ChIJEUeXhIBw8TkRFA3z4MXQ-AU", "plus_code": {"compound_code": "PC9C+VP Tola Parasi, Bihar, India", "global_code": "7MP8PC9C+VP"}, "rating": 1.3, "reference": "ChIJEUeXhIBw8TkRFA3z4MXQ-AU", "scope": "GOOGLE", "types": ["school", "point_of_interest", "establishment"], "user_ratings_total": 4, "vicinity": "Tola Parasi"}, {"business_status": "OPERATIONAL", "geometry": {"location": {"lat": 24.72805679999999, "lng": 86.4327435}, "viewport": {"northeast": {"lat": 24.7294085302915, "lng": 86.43411018029151}, "southwest": {"lat": 24.7267105697085, "lng": 86.43141221970849}}}, "icon": "https://maps.gstatic.com/mapfiles/place_api/icons/v1/png_71/school-71.png", "icon_background_color": "#7B9EB0", "icon_mask_base_uri": "https://maps.gstatic.com/mapfiles/place_api/icons/v2/school_pinlet", "name": "Lok Shiksha Kendra Chain", "place_id": "ChIJ31Y6wxxx8TkRBmhv_Cr83-Q", "plus_code": {"compound_code": "PCHM+63 Tola Naugain, Bihar, India", "global_code": "7MP8PCHM+63"}, "reference": "ChIJ31Y6wxxx8TkRBmhv_Cr83-Q", "scope": "GOOGLE", "types": ["school", "point_of_interest", "establishment"], "vicinity": "Tola Naugain"}], "status": "OK"}