{"html_attributions": [], "results": [{"business_status": "OPERATIONAL", "geometry": {"location": {"lat": 24.3925275, "lng": 86.5300967}, "viewport": {"northeast": {"lat": 24.3938974802915, "lng": 86.53139523029151}, "southwest": {"lat": 24.3911995197085, "lng": 86.52869726970849}}}, "icon": "https://maps.gstatic.com/mapfiles/place_api/icons/v1/png_71/school-71.png", "icon_background_color": "#7B9EB0", "icon_mask_base_uri": "https://maps.gstatic.com/mapfiles/place_api/icons/v2/school_pinlet", "name": "Government Upgraded Middle School Basuliya", "photos": [{"height": 1080, "html_attributions": ["<a href=\"https://maps.google.com/maps/contrib/101942837705794179603\">Anurag Bibhor</a>"], "photo_reference": "Aap_uEDhXxLWGHq5uiex3zpZFWgs19SpFFd6O57iOT2-Mdvno1CkIfuXBA3BhNAZVLIUXhlMV8uhQ_XINvc1iSWrKea39-kH83N_HT1PPz_iSt8tE4bQvvR56zAAqs4SbGviPnGeyIWgA4CbF6c5FgfWYWcgwHgsouhQMxtcdVJHjky3i-7p", "width": 1920}], "place_id": "ChIJ6c0f8tdB8TkR8D-P4x44Ovk", "plus_code": {"compound_code": "9GVJ+22 Basulia, Jharkhand, India", "global_code": "7MP89GVJ+22"}, "rating": 5, "reference": "ChIJ6c0f8tdB8TkR8D-P4x44Ovk", "scope": "GOOGLE", "types": ["school", "point_of_interest", "establishment"], "user_ratings_total": 1, "vicinity": "Unnamed Road"}, {"business_status": "OPERATIONAL", "geometry": {"location": {"lat": 24.4057401, "lng": 86.5253541}, "viewport": {"northeast": {"lat": 24.4072074802915, "lng": 86.5267356302915}, "southwest": {"lat": 24.40450951970849, "lng": 86.52403766970849}}}, "icon": "https://maps.gstatic.com/mapfiles/place_api/icons/v1/png_71/school-71.png", "icon_background_color": "#7B9EB0", "icon_mask_base_uri": "https://maps.gstatic.com/mapfiles/place_api/icons/v2/school_pinlet", "name": "Government Upgraded Primary School Tatkio", "photos": [{"height": 4608, "html_attributions": ["<a href=\"https://maps.google.com/maps/contrib/116209246120850673061\">Anurag Bibhor</a>"], "photo_reference": "Aap_uECBgZhXEoUqp1r-Bc8fdbIA8ZcpuMiU0WGJ5Qv_66MnCdOEL_5TBQmm4pBWdrmkXWpTHMyYr6Kx1PzdzYaEzPwGYwxdWsnQJXClkUPClIE9p28-nxomzKmFOPJhsqqIHAtziiLTZ_qyHcFkspveLxFfFBwpsYNofKdTIIlR4dcQnvH_", "width": 2218}], "place_id": "ChIJreYvbHpB8TkRoq-9l274kfQ", "reference": "ChIJreYvbHpB8TkRoq-9l274kfQ", "scope": "GOOGLE", "types": ["school", "point_of_interest", "establishment"], "vicinity": "CG4G+74X, Tatkio"}], "status": "OK"}