{"html_attributions": [], "results": [{"business_status": "OPERATIONAL", "geometry": {"location": {"lat": 25.8903602, "lng": 89.706797}, "viewport": {"northeast": {"lat": 25.89172338029151, "lng": 89.7083554802915}, "southwest": {"lat": 25.8890254197085, "lng": 89.7056575197085}}}, "icon": "https://maps.gstatic.com/mapfiles/place_api/icons/v1/png_71/hospital-71.png", "icon_background_color": "#F88181", "icon_mask_base_uri": "https://maps.gstatic.com/mapfiles/place_api/icons/v2/hospital-H_pinlet", "name": "Bhitarbanda Health Centre", "photos": [{"height": 1080, "html_attributions": ["<a href=\"https://maps.google.com/maps/contrib/117561256320262514977\">Rana Google</a>"], "photo_reference": "Aap_uEBY8XmyiIwHwm71eyRcwj2C1Mejj4iO65ElKJTh1meJYAPc0RNCMtVaD5T4rm5inai41pBcCOlTpw3uAdO5-Y7iHvgkJ0TDkbIb72QO2pFMS4uaDSShQJ3DS4TgreqtTHxc4VPHsnm0mtlt5bqsrCPDx1ZSGkHt7Iz7qlOXjovbRFzG", "width": 1920}], "place_id": "ChIJ6RzJsnu44jkReYGPIH4fxBE", "rating": 5, "reference": "ChIJ6RzJsnu44jkReYGPIH4fxBE", "scope": "GOOGLE", "types": ["hospital", "health", "point_of_interest", "establishment"], "user_ratings_total": 1, "vicinity": "VPR4+4PV"}], "status": "OK"}