{"html_attributions": [], "results": [{"business_status": "OPERATIONAL", "geometry": {"location": {"lat": 23.6046072, "lng": 86.4216683}, "viewport": {"northeast": {"lat": 23.6060065302915, "lng": 86.42316078029151}, "southwest": {"lat": 23.6033085697085, "lng": 86.42046281970849}}}, "icon": "https://maps.gstatic.com/mapfiles/place_api/icons/v1/png_71/school-71.png", "icon_background_color": "#7B9EB0", "icon_mask_base_uri": "https://maps.gstatic.com/mapfiles/place_api/icons/v2/school_pinlet", "name": "middle school madhra", "place_id": "ChIJk0L3si2R9jkRNW6c3yClUaY", "rating": 3, "reference": "ChIJk0L3si2R9jkRNW6c3yClUaY", "scope": "GOOGLE", "types": ["school", "point_of_interest", "establishment"], "user_ratings_total": 2, "vicinity": "JC3C+RMV, Marra"}, {"business_status": "OPERATIONAL", "geometry": {"location": {"lat": 23.6046705, "lng": 86.42159149999999}, "viewport": {"northeast": {"lat": 23.6060789302915, "lng": 86.42310498029151}, "southwest": {"lat": 23.6033809697085, "lng": 86.42040701970849}}}, "icon": "https://maps.gstatic.com/mapfiles/place_api/icons/v1/png_71/school-71.png", "icon_background_color": "#7B9EB0", "icon_mask_base_uri": "https://maps.gstatic.com/mapfiles/place_api/icons/v2/school_pinlet", "name": "Middle School Marrah", "place_id": "ChIJBw75yaGQ9jkRVSiNkbkjtG0", "plus_code": {"compound_code": "JC3C+VJ Marra, Jharkhand, India", "global_code": "7MM8JC3C+VJ"}, "reference": "ChIJBw75yaGQ9jkRVSiNkbkjtG0", "scope": "GOOGLE", "types": ["school", "point_of_interest", "establishment"], "vicinity": "Marra"}, {"business_status": "OPERATIONAL", "geometry": {"location": {"lat": 23.6177085, "lng": 86.4250375}, "viewport": {"northeast": {"lat": 23.6190621802915, "lng": 86.4263746802915}, "southwest": {"lat": 23.61636421970849, "lng": 86.4236767197085}}}, "icon": "https://maps.gstatic.com/mapfiles/place_api/icons/v1/png_71/school-71.png", "icon_background_color": "#7B9EB0", "icon_mask_base_uri": "https://maps.gstatic.com/mapfiles/place_api/icons/v2/school_pinlet", "name": "Lankatand (Kali Mandir)", "photos": [{"height": 1280, "html_attributions": ["<a href=\"https://maps.google.com/maps/contrib/105246200548977512166\">cricket Stories</a>"], "photo_reference": "Aap_uEAkYfLkykUE8t9pTG5smz7uCAcSWen_Q9kWadLCUmod3TLS3oqaZslxMhwTSUpF6B7M3N4iEhCKsyPBZmN71DYqT97ONp1aJtwZs1Lq_5KGgNXnQ0V7No4Te7u3lJo-m0LiZZ1JsU6B7KCrIQam6EeecbRMYOr_HBxZpd35W6th-xql", "width": 720}], "place_id": "ChIJyV79tyKR9jkRl2PRLwZ_Iyo", "plus_code": {"compound_code": "JC9G+32 Polkiri, Jharkhand, India", "global_code": "7MM8JC9G+32"}, "reference": "ChIJyV79tyKR9jkRl2PRLwZ_Iyo", "scope": "GOOGLE", "types": ["school", "point_of_interest", "establishment"], "vicinity": "Unnamed Road, Polkiri"}, {"business_status": "OPERATIONAL", "geometry": {"location": {"lat": 23.6131918, "lng": 86.4361703}, "viewport": {"northeast": {"lat": 23.6145675802915, "lng": 86.4375575302915}, "southwest": {"lat": 23.6118696197085, "lng": 86.4348595697085}}}, "icon": "https://maps.gstatic.com/mapfiles/place_api/icons/v1/png_71/school-71.png", "icon_background_color": "#7B9EB0", "icon_mask_base_uri": "https://maps.gstatic.com/mapfiles/place_api/icons/v2/school_pinlet", "name": "Prathamik Vidalaya Amdiha", "opening_hours": {"open_now": false}, "place_id": "ChIJq77tufaR9jkRV5mLQvJHRzM", "plus_code": {"compound_code": "JC7P+7F Amdiha, Jharkhand, India", "global_code": "7MM8JC7P+7F"}, "reference": "ChIJq77tufaR9jkRV5mLQvJHRzM", "scope": "GOOGLE", "types": ["school", "point_of_interest", "establishment"], "vicinity": "Unnamed Road, Amdiha"}, {"business_status": "OPERATIONAL", "geometry": {"location": {"lat": 23.6152416, "lng": 86.4157899}, "viewport": {"northeast": {"lat": 23.6168667302915, "lng": 86.4171820302915}, "southwest": {"lat": 23.6141687697085, "lng": 86.41448406970848}}}, "icon": "https://maps.gstatic.com/mapfiles/place_api/icons/v1/png_71/school-71.png", "icon_background_color": "#7B9EB0", "icon_mask_base_uri": "https://maps.gstatic.com/mapfiles/place_api/icons/v2/school_pinlet", "name": "L P Shool Bhoski", "place_id": "ChIJFwk9uieb9jkRlb0TkoIO8qo", "reference": "ChIJFwk9uieb9jkRlb0TkoIO8qo", "scope": "GOOGLE", "types": ["school", "point_of_interest", "establishment"], "vicinity": "JC88+38V, Bhusk"}, {"business_status": "OPERATIONAL", "geometry": {"location": {"lat": 23.6152624, "lng": 86.41564}, "viewport": {"northeast": {"lat": 23.6168771302915, "lng": 86.4171070802915}, "southwest": {"lat": 23.6141791697085, "lng": 86.4144091197085}}}, "icon": "https://maps.gstatic.com/mapfiles/place_api/icons/v1/png_71/school-71.png", "icon_background_color": "#7B9EB0", "icon_mask_base_uri": "https://maps.gstatic.com/mapfiles/place_api/icons/v2/school_pinlet", "name": "Hanuman mandir bhoski", "place_id": "ChIJ44JyQgKb9jkR4CFfqBE-GtY", "rating": 5, "reference": "ChIJ44JyQgKb9jkR4CFfqBE-GtY", "scope": "GOOGLE", "types": ["school", "point_of_interest", "establishment"], "user_ratings_total": 1, "vicinity": "JC88+472, Bhuski"}, {"business_status": "OPERATIONAL", "geometry": {"location": {"lat": 23.6050376, "lng": 86.43903829999999}, "viewport": {"northeast": {"lat": 23.6064261802915, "lng": 86.44041423029151}, "southwest": {"lat": 23.6037282197085, "lng": 86.4377162697085}}}, "icon": "https://maps.gstatic.com/mapfiles/place_api/icons/v1/png_71/school-71.png", "icon_background_color": "#7B9EB0", "icon_mask_base_uri": "https://maps.gstatic.com/mapfiles/place_api/icons/v2/school_pinlet", "name": "N P S Tekora", "place_id": "ChIJy3JjNTiR9jkRlzh3sjc6-ns", "plus_code": {"compound_code": "JC4Q+2J Tekora, West Bengal, India", "global_code": "7MM8JC4Q+2J"}, "reference": "ChIJy3JjNTiR9jkRlzh3sjc6-ns", "scope": "GOOGLE", "types": ["primary_school", "school", "point_of_interest", "establishment"], "vicinity": "Tekora"}], "status": "OK"}