{"html_attributions": [], "results": [{"business_status": "OPERATIONAL", "geometry": {"location": {"lat": 23.4881918, "lng": 85.7502588}, "viewport": {"northeast": {"lat": 23.4895407802915, "lng": 85.7516077802915}, "southwest": {"lat": 23.4868428197085, "lng": 85.74890981970849}}}, "icon": "https://maps.gstatic.com/mapfiles/place_api/icons/v1/png_71/school-71.png", "icon_background_color": "#7B9EB0", "icon_mask_base_uri": "https://maps.gstatic.com/mapfiles/place_api/icons/v2/school_pinlet", "name": "Primary school Dhordhora", "photos": [{"height": 720, "html_attributions": ["<a href=\"https://maps.google.com/maps/contrib/109774392931883756972\">Ravi Kumar</a>"], "photo_reference": "Aap_uEABJhlOPduw7KHpqBvHkyMrkeKqUIub-fwrhfrL-7eoh_T1z-ENlyBosRtcxokPJ3Jz7bUlQy2L-OydF111nI9dNmSVv_7snUAQflzBtIQGapOnsMluOGyt81N24bm1W6JzwZI_dqXl9-p8Pk1vzW_4yfuANCN5Wm_H9bXDxwQaXHNQ", "width": 1280}], "place_id": "ChIJdcvkWOVR9DkRZ3DCPC64O1w", "rating": 5, "reference": "ChIJdcvkWOVR9DkRZ3DCPC64O1w", "scope": "GOOGLE", "types": ["school", "point_of_interest", "establishment"], "user_ratings_total": 1, "vicinity": "FQQ2+74C, Korambe"}, {"business_status": "OPERATIONAL", "geometry": {"location": {"lat": 23.497667, "lng": 85.73615769999999}, "viewport": {"northeast": {"lat": 23.4994830302915, "lng": 85.7380801802915}, "southwest": {"lat": 23.49678506970849, "lng": 85.73538221970848}}}, "icon": "https://maps.gstatic.com/mapfiles/place_api/icons/v1/png_71/school-71.png", "icon_background_color": "#7B9EB0", "icon_mask_base_uri": "https://maps.gstatic.com/mapfiles/place_api/icons/v2/school_pinlet", "name": "Siddhartha International Acadmey", "place_id": "ChIJs0dWO-ZR9DkRrQRQvIyz7cc", "plus_code": {"compound_code": "FPXP+3F Purabdih alias Kudapalu, Jharkhand, India", "global_code": "7MM7FPXP+3F"}, "rating": 5, "reference": "ChIJs0dWO-ZR9DkRrQRQvIyz7cc", "scope": "GOOGLE", "types": ["school", "point_of_interest", "establishment"], "user_ratings_total": 1, "vicinity": "Purabdih alias Kudapalu"}], "status": "OK"}