{"html_attributions": [], "results": [{"business_status": "OPERATIONAL", "geometry": {"location": {"lat": 23.8331911, "lng": 86.43043279999999}, "viewport": {"northeast": {"lat": 23.8343715302915, "lng": 86.4317971302915}, "southwest": {"lat": 23.83167356970849, "lng": 86.4290991697085}}}, "icon": "https://maps.gstatic.com/mapfiles/place_api/icons/v1/png_71/hospital-71.png", "icon_background_color": "#F88181", "icon_mask_base_uri": "https://maps.gstatic.com/mapfiles/place_api/icons/v2/hospital-H_pinlet", "name": "Sarwamangla Nursing Home", "opening_hours": {"open_now": true}, "photos": [{"height": 3456, "html_attributions": ["<a href=\"https://maps.google.com/maps/contrib/106649152851281463337\">Sarwamangla Nursing Home</a>"], "photo_reference": "Aap_uEB6UU2drTlEQuBkammsnqp0s57TpXll0qiQC-eJXColixbGOgkinH4t2yRTjT57uXAFTgiJZf8yWBB-ivsQJtdwtNogVoW9MIQKJYnhg5ju6oYJS22gtOa2zUYPWAtRUTwONbjYStbXMNNEoE5EiWyb44FZFLX3F5hrwnsYvCdOGtMz", "width": 5184}], "place_id": "ChIJP7SDu0W79jkR3RNvSC3ZHSA", "plus_code": {"compound_code": "RCMJ+75 Susnilewa, Jharkhand, India", "global_code": "7MM8RCMJ+75"}, "rating": 3.4, "reference": "ChIJP7SDu0W79jkR3RNvSC3ZHSA", "scope": "GOOGLE", "types": ["hospital", "health", "point_of_interest", "establishment"], "user_ratings_total": 27, "vicinity": "Near Hawai Adda Hirak Road, Memco More, Post Nag Nagar, Susnilewa"}, {"business_status": "OPERATIONAL", "geometry": {"location": {"lat": 23.8330758, "lng": 86.4298135}, "viewport": {"northeast": {"lat": 23.8342945802915, "lng": 86.43116938029151}, "southwest": {"lat": 23.8315966197085, "lng": 86.42847141970849}}}, "icon": "https://maps.gstatic.com/mapfiles/place_api/icons/v1/png_71/hospital-71.png", "icon_background_color": "#F88181", "icon_mask_base_uri": "https://maps.gstatic.com/mapfiles/place_api/icons/v2/hospital-H_pinlet", "name": "Kasturba Seva Sadan", "photos": [{"height": 1080, "html_attributions": ["<a href=\"https://maps.google.com/maps/contrib/114713135985733205546\">Kasturba Seva Sadan</a>"], "photo_reference": "Aap_uEAuMbI1RL7dlhRfTLZVGRO8F5R5tvOVtMBwLyKE4T-qp-Rpj1TY6bcCJP81CYJsiOCzgXW9aW7E5lOQ3geF0ScJEAULqsN9Uc_FUVsPzF68rP6FGHuT5I-gUaEo0sOPXIOr6R2tWA5wIbPgbLZIP38nrOFpTewM9-G-evhk-MycSmTH", "width": 1920}], "place_id": "ChIJF6XUkEW79jkRa1hEU6GnDNM", "plus_code": {"compound_code": "RCMH+6W Dhanbad, Jharkhand, India", "global_code": "7MM8RCMH+6W"}, "rating": 4.8, "reference": "ChIJF6XUkEW79jkRa1hEU6GnDNM", "scope": "GOOGLE", "types": ["hospital", "health", "point_of_interest", "establishment"], "user_ratings_total": 6, "vicinity": "Memko More, Hirak Point, Dhanbad"}, {"business_status": "OPERATIONAL", "geometry": {"location": {"lat": 23.8332006, "lng": 86.43096849999999}, "viewport": {"northeast": {"lat": 23.8343965802915, "lng": 86.4323314302915}, "southwest": {"lat": 23.83169861970849, "lng": 86.42963346970849}}}, "icon": "https://maps.gstatic.com/mapfiles/place_api/icons/v1/png_71/hospital-71.png", "icon_background_color": "#F88181", "icon_mask_base_uri": "https://maps.gstatic.com/mapfiles/place_api/icons/v2/hospital-H_pinlet", "name": "Teeth and pearl dental clinic", "place_id": "ChIJxRJ7Njq79jkRTMo1bKanzFU", "plus_code": {"compound_code": "RCMJ+79 Dhanbad, Jharkhand, India", "global_code": "7MM8RCMJ+79"}, "reference": "ChIJxRJ7Njq79jkRTMo1bKanzFU", "scope": "GOOGLE", "types": ["hospital", "health", "point_of_interest", "establishment"], "vicinity": "Memco, more, Dhanbad"}, {"business_status": "OPERATIONAL", "geometry": {"location": {"lat": 23.8334336, "lng": 86.4322506}, "viewport": {"northeast": {"lat": 23.8346877302915, "lng": 86.4333881302915}, "southwest": {"lat": 23.8319897697085, "lng": 86.4306901697085}}}, "icon": "https://maps.gstatic.com/mapfiles/place_api/icons/v1/png_71/hospital-71.png", "icon_background_color": "#F88181", "icon_mask_base_uri": "https://maps.gstatic.com/mapfiles/place_api/icons/v2/hospital-H_pinlet", "name": "Shree Ram Hospital", "opening_hours": {"open_now": true}, "photos": [{"height": 3120, "html_attributions": ["<a href=\"https://maps.google.com/maps/contrib/102015675237706181326\">Kr Nirmal</a>"], "photo_reference": "Aap_uEBK0rjC3V2ada8vpV5FG4iNfGjLF01gQ3Ts8CaId541h-_FFFYuec5NBZxAvx49dlXg6wV1csyTbLdggeH9sZNe3fxrvtz58baGA4DX9tMyamK33eWqgrYZJMNoSIi80Bofpnd0x4RYq3gobUW6SUa3bFGKIOAYGfRe01nUcI82jCH8", "width": 4160}], "place_id": "ChIJt2tpRkS79jkRdQbRDnpNKRs", "plus_code": {"compound_code": "RCMJ+9W Susnilewa, Jharkhand, India", "global_code": "7MM8RCMJ+9W"}, "rating": 3.6, "reference": "ChIJt2tpRkS79jkRdQbRDnpNKRs", "scope": "GOOGLE", "types": ["hospital", "health", "point_of_interest", "establishment"], "user_ratings_total": 13, "vicinity": "Barwaada Road, Susnilewa"}, {"business_status": "OPERATIONAL", "geometry": {"location": {"lat": 23.8261423, "lng": 86.437707}, "viewport": {"northeast": {"lat": 23.8275064302915, "lng": 86.4390254802915}, "southwest": {"lat": 23.8248084697085, "lng": 86.4363275197085}}}, "icon": "https://maps.gstatic.com/mapfiles/place_api/icons/v1/png_71/hospital-71.png", "icon_background_color": "#F88181", "icon_mask_base_uri": "https://maps.gstatic.com/mapfiles/place_api/icons/v2/hospital-H_pinlet", "name": "Sabsa sasta dukan dhanbad", "opening_hours": {"open_now": true}, "photos": [{"height": 500, "html_attributions": ["<a href=\"https://maps.google.com/maps/contrib/116797224457222638421\">Sabsa sasta dukan dhanbad</a>"], "photo_reference": "Aap_uECZ4g0gxTrN6hDQf7vbdBqBCQcfgL3ceaU6D_sUK7dgDv1Oh3_gDpLv6Y5h7tPXZRV2Ndhqj3ao4CyK_rSBQbFxSvX-Z3ekJL3esXip3VW65eWeDEtBzexjir9BH0qOCtnoNcEwLDUjFuZagEHCSOCUK65oz6_CfR7-d_F7iv099H-l", "width": 500}], "place_id": "ChIJ9bm1cly79jkRYXI-EcQviAY", "plus_code": {"compound_code": "RCGQ+F3 Dhanbad, Jharkhand, India", "global_code": "7MM8RCGQ+F3"}, "reference": "ChIJ9bm1cly79jkRYXI-EcQviAY", "scope": "GOOGLE", "types": ["hospital", "health", "point_of_interest", "establishment"], "vicinity": "Rani bandh, GIC Colony, Dhanbad"}, {"business_status": "OPERATIONAL", "geometry": {"location": {"lat": 23.8236485, "lng": 86.4148354}, "viewport": {"northeast": {"lat": 23.8249727802915, "lng": 86.41616753029149}, "southwest": {"lat": 23.8222748197085, "lng": 86.41346956970848}}}, "icon": "https://maps.gstatic.com/mapfiles/place_api/icons/v1/png_71/hospital-71.png", "icon_background_color": "#F88181", "icon_mask_base_uri": "https://maps.gstatic.com/mapfiles/place_api/icons/v2/hospital-H_pinlet", "name": "Best Ambulance Services Dhanbad", "opening_hours": {"open_now": true}, "place_id": "ChIJn1uvx4il9jkRlL-cUiYcBPA", "plus_code": {"compound_code": "RCF7+FW Dhanbad, Jharkhand, India", "global_code": "7MM8RCF7+FW"}, "reference": "ChIJn1uvx4il9jkRlL-cUiYcBPA", "scope": "GOOGLE", "types": ["hospital", "health", "point_of_interest", "establishment"], "vicinity": "Bhuli Hirak Road, Jharudih, Dhanbad"}], "status": "OK"}