{"html_attributions": [], "results": [{"business_status": "OPERATIONAL", "geometry": {"location": {"lat": 27.7218842, "lng": 80.65404520000001}, "viewport": {"northeast": {"lat": 27.7232052802915, "lng": 80.65548598029152}, "southwest": {"lat": 27.7205073197085, "lng": 80.6527880197085}}}, "icon": "https://maps.gstatic.com/mapfiles/place_api/icons/v1/png_71/school-71.png", "icon_background_color": "#7B9EB0", "icon_mask_base_uri": "https://maps.gstatic.com/mapfiles/place_api/icons/v2/school_pinlet", "name": "Govt. Primary School, Daheliya Bibipur", "photos": [{"height": 3120, "html_attributions": ["<a href=\"https://maps.google.com/maps/contrib/112990907617567354935\">Devendra Kumar Maurya</a>"], "photo_reference": "Aap_uEAwESHKHbMzAiK2fHCHB2UC9f2fqReolNR7aPULlo8DM4AkdUDQf3BpGf8mPfaGAwpmRNTW7dtq6KOnFzBGlbQHQy7BCEFWHSe-tR-xntqZsE1keN_WN9xB5AZ6CSMLiokNE6JSvU60fK0SFKsEAJW19hdFvBYOXE2dVJcpCp8SnwRV", "width": 4160}], "place_id": "ChIJYTf4kz8vnzkRx8TAhrj6pCA", "rating": 3.5, "reference": "ChIJYTf4kz8vnzkRx8TAhrj6pCA", "scope": "GOOGLE", "types": ["primary_school", "school", "point_of_interest", "establishment"], "user_ratings_total": 2, "vicinity": "PMC3+QJ3, Bibipur"}, {"business_status": "OPERATIONAL", "geometry": {"location": {"lat": 27.7199906, "lng": 80.6379704}, "viewport": {"northeast": {"lat": 27.7212645802915, "lng": 80.63943228029152}, "southwest": {"lat": 27.71856661970849, "lng": 80.6367343197085}}}, "icon": "https://maps.gstatic.com/mapfiles/place_api/icons/v1/png_71/school-71.png", "icon_background_color": "#7B9EB0", "icon_mask_base_uri": "https://maps.gstatic.com/mapfiles/place_api/icons/v2/school_pinlet", "name": "PS Kanya Hajipur", "photos": [{"height": 3120, "html_attributions": ["<a href=\"https://maps.google.com/maps/contrib/101594535052483329746\">Mo Irfan Ansari</a>"], "photo_reference": "Aap_uECYtGcEWU6QXORsIB08JREJTb-TSLkrZNTV_Sdi7LEGHGCdaCSOMLFqlbSDTBw9oWJtfMCkRelnpnKdOOLYbV_McnwJ35gla7PL0XgT1vWDLzIpvzxMtlCgYpKklQ3rs154z_u4eX4jZFBjO2eHKQdhFjjzR7hb_ty5stEQ1lFmV5LO", "width": 4160}], "place_id": "ChIJf9jqoV4vnzkRf4cV2Oz6gow", "rating": 5, "reference": "ChIJf9jqoV4vnzkRf4cV2Oz6gow", "scope": "GOOGLE", "types": ["school", "point_of_interest", "establishment"], "user_ratings_total": 1, "vicinity": "PJ9Q+X5X, Hajipur"}, {"business_status": "OPERATIONAL", "geometry": {"location": {"lat": 27.7160188, "lng": 80.6350052}, "viewport": {"northeast": {"lat": 27.7173659802915, "lng": 80.6365060302915}, "southwest": {"lat": 27.71466801970849, "lng": 80.6338080697085}}}, "icon": "https://maps.gstatic.com/mapfiles/place_api/icons/v1/png_71/school-71.png", "icon_background_color": "#7B9EB0", "icon_mask_base_uri": "https://maps.gstatic.com/mapfiles/place_api/icons/v2/school_pinlet", "name": "\u0928\u093f\u0935\u093e\u0938 \u0924\u093e\u0930\u093f\u0915 \u0916\u093e\u0901\u0928", "opening_hours": {"open_now": true}, "photos": [{"height": 954, "html_attributions": ["<a href=\"https://maps.google.com/maps/contrib/116597723102741942861\">Sitapur fance clube U.P.</a>"], "photo_reference": "Aap_uEDgCyAH9ejkgCH82lDUUyMoxSXXWBeXFsRa5x_EAG7qqYA86aiqPUDGPzw4-sA8Ilt_QXuQoEOYsD0HyQ3nEd0JfKCPezlAsLBcQQzfcuuVAx_1Z_fyfPQ77P-9E18Nb8-sNlbk4Uob0eEUimn2dKlxWo0HILVQ0sT2yHu8RfsTgiSP", "width": 716}], "place_id": "ChIJYd1qzpQvnzkR9VTXxMwQPPE", "reference": "ChIJYd1qzpQvnzkR9VTXxMwQPPE", "scope": "GOOGLE", "types": ["school", "point_of_interest", "establishment"], "vicinity": "PJ8P+C22, Hajipur"}], "status": "OK"}