{"html_attributions": [], "results": [{"business_status": "OPERATIONAL", "geometry": {"location": {"lat": 27.5044031, "lng": 80.793053}, "viewport": {"northeast": {"lat": 27.5058199302915, "lng": 80.7944596302915}, "southwest": {"lat": 27.5031219697085, "lng": 80.79176166970849}}}, "icon": "https://maps.gstatic.com/mapfiles/place_api/icons/v1/png_71/school-71.png", "icon_background_color": "#7B9EB0", "icon_mask_base_uri": "https://maps.gstatic.com/mapfiles/place_api/icons/v2/school_pinlet", "name": "Shaurya Convent School", "opening_hours": {"open_now": true}, "place_id": "ChIJYyvO2PTTnjkRxuFywVYCd7w", "plus_code": {"compound_code": "GQ3V+Q6 Am Khera, Uttar Pradesh, India", "global_code": "7MV2GQ3V+Q6"}, "reference": "ChIJYyvO2PTTnjkRxuFywVYCd7w", "scope": "GOOGLE", "types": ["school", "point_of_interest", "establishment"], "vicinity": "Ashrafpur, Khairabad, Sitapur"}, {"business_status": "OPERATIONAL", "geometry": {"location": {"lat": 27.5028983, "lng": 80.7953367}, "viewport": {"northeast": {"lat": 27.50426768029151, "lng": 80.79665383029149}, "southwest": {"lat": 27.5015697197085, "lng": 80.79395586970848}}}, "icon": "https://maps.gstatic.com/mapfiles/place_api/icons/v1/png_71/school-71.png", "icon_background_color": "#7B9EB0", "icon_mask_base_uri": "https://maps.gstatic.com/mapfiles/place_api/icons/v2/school_pinlet", "name": "P.S. ASHRAFPUR", "place_id": "ChIJHenVibzTnjkRgX8PlhP5bC4", "plus_code": {"compound_code": "GQ3W+54 Am Khera, Uttar Pradesh, India", "global_code": "7MV2GQ3W+54"}, "reference": "ChIJHenVibzTnjkRgX8PlhP5bC4", "scope": "GOOGLE", "types": ["primary_school", "school", "point_of_interest", "establishment"], "vicinity": "Unnamed Road, Am Khera"}], "status": "OK"}