{"html_attributions": [], "results": [{"business_status": "OPERATIONAL", "geometry": {"location": {"lat": 27.252618, "lng": 80.10247199999999}, "viewport": {"northeast": {"lat": 27.25386428029151, "lng": 80.10373683029151}, "southwest": {"lat": 27.2511663197085, "lng": 80.10103886970849}}}, "icon": "https://maps.gstatic.com/mapfiles/place_api/icons/v1/png_71/school-71.png", "icon_background_color": "#7B9EB0", "icon_mask_base_uri": "https://maps.gstatic.com/mapfiles/place_api/icons/v2/school_pinlet", "name": "Primary school kahatra", "photos": [{"height": 1080, "html_attributions": ["<a href=\"https://maps.google.com/maps/contrib/102736713622438208757\">surya H S I</a>"], "photo_reference": "Aap_uECbBvAfl7s52MaZUtAC62qL9jkFwzk01guZUXk9awN9t-xB--7wFI3gOVyZ5GVyTRdMdQXLVmz34oHHUsi6dpu_Zu3y-tuu7bJRRrJ9A56aR4kIuVbvD8x3ygYhbKyjWL5rIoJeLacrpNUGqgaRdtH34YCqb8XbRn2ayuzzXw7yp_qU", "width": 1920}], "place_id": "ChIJSSvXhHP1njkRZ60yzmCjlSg", "plus_code": {"compound_code": "7432+2X Bhitha, Uttar Pradesh, India", "global_code": "7MV27432+2X"}, "reference": "ChIJSSvXhHP1njkRZ60yzmCjlSg", "scope": "GOOGLE", "types": ["school", "point_of_interest", "establishment"], "vicinity": "Unnamed Road"}, {"business_status": "OPERATIONAL", "geometry": {"location": {"lat": 27.2528178, "lng": 80.1008683}, "viewport": {"northeast": {"lat": 27.2542010802915, "lng": 80.1021104802915}, "southwest": {"lat": 27.2515031197085, "lng": 80.0994125197085}}}, "icon": "https://maps.gstatic.com/mapfiles/place_api/icons/v1/png_71/school-71.png", "icon_background_color": "#7B9EB0", "icon_mask_base_uri": "https://maps.gstatic.com/mapfiles/place_api/icons/v2/school_pinlet", "name": "Rudra Aawashey Academy School", "opening_hours": {"open_now": true}, "photos": [{"height": 620, "html_attributions": ["<a href=\"https://maps.google.com/maps/contrib/106984952837042149124\">Rudra Aawashey Academy</a>"], "photo_reference": "Aap_uED9u5byrYS34iueAw3m82RFUHrhTASaPsygTZVKmhiE1LAn8FUAJLy7keky6PDva8M0-k0aruuT47frRpZBfsSK5hRtIk8SWBP-v92PZ0A853OQwMJhOr4kk4fl8iV7LkXYRliX-IFH_ct3Fok826Fqp0AYenB4uGZywkhX0z0aoGVp", "width": 1102}], "place_id": "ChIJY_4LfO_1njkRNiNaXce3aS0", "plus_code": {"compound_code": "7432+48 Bhitha, Uttar Pradesh, India", "global_code": "7MV27432+48"}, "rating": 4.6, "reference": "ChIJY_4LfO_1njkRNiNaXce3aS0", "scope": "GOOGLE", "types": ["school", "point_of_interest", "establishment"], "user_ratings_total": 10, "vicinity": "Uttar Pradesh kahatra"}], "status": "OK"}