{"html_attributions": [], "results": [{"business_status": "OPERATIONAL", "geometry": {"location": {"lat": 27.44045939999999, "lng": 80.211246}, "viewport": {"northeast": {"lat": 27.4419449802915, "lng": 80.2126534302915}, "southwest": {"lat": 27.4392470197085, "lng": 80.20995546970849}}}, "icon": "https://maps.gstatic.com/mapfiles/place_api/icons/v1/png_71/school-71.png", "icon_background_color": "#7B9EB0", "icon_mask_base_uri": "https://maps.gstatic.com/mapfiles/place_api/icons/v2/school_pinlet", "name": "Primary school Birhana,Block-Tadiyawan", "opening_hours": {"open_now": false}, "place_id": "ChIJYbKFP7X7njkRN1m6QfDpZDM", "rating": 4, "reference": "ChIJYbKFP7X7njkRN1m6QfDpZDM", "scope": "GOOGLE", "types": ["school", "point_of_interest", "establishment"], "user_ratings_total": 1, "vicinity": "C6R6+5FQ, Sandila"}], "status": "OK"}