{"html_attributions": [], "results": [{"business_status": "OPERATIONAL", "geometry": {"location": {"lat": 27.1354588, "lng": 80.6097418}, "viewport": {"northeast": {"lat": 27.1367581802915, "lng": 80.61114283029151}, "southwest": {"lat": 27.13406021970849, "lng": 80.60844486970849}}}, "icon": "https://maps.gstatic.com/mapfiles/place_api/icons/v1/png_71/generic_business-71.png", "icon_background_color": "#7B9EB0", "icon_mask_base_uri": "https://maps.gstatic.com/mapfiles/place_api/icons/v2/generic_pinlet", "name": "Siddiqui Clinic", "place_id": "ChIJRyoS8CG6njkRnrYbcHX1Peg", "rating": 5, "reference": "ChIJRyoS8CG6njkRnrYbcHX1Peg", "scope": "GOOGLE", "types": ["doctor", "health", "point_of_interest", "establishment"], "user_ratings_total": 1, "vicinity": "4JP5+5VQ, Dhikunni"}], "status": "OK"}