{"html_attributions": [], "results": [{"business_status": "OPERATIONAL", "geometry": {"location": {"lat": 23.4365594, "lng": 86.2844131}, "viewport": {"northeast": {"lat": 23.43791278029151, "lng": 86.2856779302915}, "southwest": {"lat": 23.4352148197085, "lng": 86.28297996970849}}}, "icon": "https://maps.gstatic.com/mapfiles/place_api/icons/v1/png_71/shopping-71.png", "icon_background_color": "#4B96F3", "icon_mask_base_uri": "https://maps.gstatic.com/mapfiles/place_api/icons/v2/shoppingcart_pinlet", "name": "Shaadi Bhandar Puja Bhandar", "place_id": "ChIJm5HdvD6D9jkRavBBJCZVVUw", "reference": "ChIJm5HdvD6D9jkRavBBJCZVVUw", "scope": "GOOGLE", "types": ["supermarket", "grocery_or_supermarket", "food", "point_of_interest", "store", "establishment"], "vicinity": "C7PM+JQF, Phusro"}], "status": "OK"}