{"html_attributions": [], "results": [{"business_status": "OPERATIONAL", "geometry": {"location": {"lat": 23.80989010000001, "lng": 86.3823159}, "viewport": {"northeast": {"lat": 23.8112335302915, "lng": 86.38366403029151}, "southwest": {"lat": 23.8085355697085, "lng": 86.38096606970849}}}, "icon": "https://maps.gstatic.com/mapfiles/place_api/icons/v1/png_71/shopping-71.png", "icon_background_color": "#4B96F3", "icon_mask_base_uri": "https://maps.gstatic.com/mapfiles/place_api/icons/v2/shoppingcart_pinlet", "name": "Abhishek Grocery", "place_id": "ChIJiYJ4Oi6j9jkRrDrcPf7cWxE", "plus_code": {"compound_code": "R95J+XW Ranguni, Jharkhand, India", "global_code": "7MM8R95J+XW"}, "reference": "ChIJiYJ4Oi6j9jkRrDrcPf7cWxE", "scope": "GOOGLE", "types": ["supermarket", "grocery_or_supermarket", "food", "point_of_interest", "store", "establishment"], "vicinity": "BHAGIRATH NIWAS, Bhuli Hirak Road, Bhuli, Ranguni"}, {"business_status": "OPERATIONAL", "geometry": {"location": {"lat": 23.8173773, "lng": 86.38429}, "viewport": {"northeast": {"lat": 23.8187006302915, "lng": 86.3856367802915}, "southwest": {"lat": 23.81600266970849, "lng": 86.38293881970849}}}, "icon": "https://maps.gstatic.com/mapfiles/place_api/icons/v1/png_71/shopping-71.png", "icon_background_color": "#4B96F3", "icon_mask_base_uri": "https://maps.gstatic.com/mapfiles/place_api/icons/v2/shoppingcart_pinlet", "name": "Sagar Sabji Dukan", "photos": [{"height": 2592, "html_attributions": ["<a href=\"https://maps.google.com/maps/contrib/116172874742079099480\">SAGAR KUMAR</a>"], "photo_reference": "Aap_uEAtoM5IiaDw4K-LATGxBtW7TEYt-KF9fTVCWPIgixV6FX0Itqk94luyd6DWxUnC1iZmHSNHzLLlxdZksZvNXsFodrURyhQdomuS_OxeH6LWR26b3TSvF02vbylk09dirhSUFmAjgBonna11Kq0xVd-UBZFROwpqaovduWQtGf-wLvPk", "width": 1944}], "place_id": "ChIJU6D8cjWl9jkRPvtiE9g9Tm0", "rating": 5, "reference": "ChIJU6D8cjWl9jkRPvtiE9g9Tm0", "scope": "GOOGLE", "types": ["supermarket", "grocery_or_supermarket", "food", "point_of_interest", "store", "establishment"], "user_ratings_total": 1, "vicinity": "R98M+XP3, Bhuli D Block, sec 8, Dhanbad"}], "status": "OK"}